AUTHORS.rst
CONTRIBUTING.rst
HISTORY.rst
LICENSE
MANIFEST.in
README.rst
requirements.txt
setup.cfg
setup.py
awsscripter/__init__.py
awsscripter.egg-info/PKG-INFO
awsscripter.egg-info/SOURCES.txt
awsscripter.egg-info/dependency_links.txt
awsscripter.egg-info/entry_points.txt
awsscripter.egg-info/not-zip-safe
awsscripter.egg-info/requires.txt
awsscripter.egg-info/top_level.txt
awsscripter/audit/AuditStatusColourer.py
awsscripter/audit/Auditor.py
awsscripter/audit/CloudTrail.py
awsscripter/audit/Controls.py
awsscripter/audit/CredReport.py
awsscripter/audit/PasswordPolicy.py
awsscripter/audit/__init__.py
awsscripter/audit/audit.py
awsscripter/audit/audit_status.py
awsscripter/billing/__init__.py
awsscripter/billing/hourlybilltoes.py
awsscripter/cli/__init__.py
awsscripter/cli/Password/__init__.py
awsscripter/cli/Password/password.py
awsscripter/cli/Password/policies.py
awsscripter/cli/audit/__init__.py
awsscripter/cli/audit/audit.py
awsscripter/cli/audit/cispaudit.py
awsscripter/cli/audit/hippaaudit.py
awsscripter/cli/audit/pcidss.py
awsscripter/cli/awsbilling/__init__.py
awsscripter/cli/awsbilling/awsbilling.py
awsscripter/cli/awsbilling/hbrtoes.py
awsscripter/cli/init/__init__.py
awsscripter/cli/init/init.py
awsscripter/cli/list/__init__.py
awsscripter/cli/list/ec2.py
awsscripter/cli/list/list.py
awsscripter/cli/monitoring/__init__.py
awsscripter/cli/monitoring/cpu.py
awsscripter/cli/monitoring/monitor.py
awsscripter/cli/security/__init__.py
awsscripter/cli/security/security.py
awsscripter/cli/security/tcp.py
awsscripter/cli/security/udp.py
awsscripter/cli/stack/__init__.py
awsscripter/cli/stack/create.py
awsscripter/cli/stack/delete.py
awsscripter/cli/stack/describe.py
awsscripter/cli/stack/execute.py
awsscripter/cli/stack/launch.py
awsscripter/cli/stack/list.py
awsscripter/cli/stack/policy.py
awsscripter/cli/stack/stack.py
awsscripter/cli/stack/status.py
awsscripter/cli/stack/template.py
awsscripter/cli/stack/update.py
awsscripter/cli/test/__init__.py
awsscripter/cli/test/password.py
awsscripter/cli/test/tcp.py
awsscripter/cli/test/udp.py
awsscripter/cli/testcommand/__init__.py
awsscripter/cli/testcommand/command1.py
awsscripter/cli/testcommand/command2.py
awsscripter/cli/testcommand/testcommand.py
