Metadata-Version: 1.1
Name: awsscripter
Version: 0.0.314
Summary: Cloud Provisioning Tool
Home-page: https://github.com/xformation/awsscripter
Author: Papu
Author-email: papu.bhattacharya@synectiks.com
License: Apache2
Keywords: awsscripter
Platform: UNKNOWN
Classifier: Development Status :: 5 - Production/Stable
Classifier: Intended Audience :: Developers
Classifier: Natural Language :: English
Classifier: Environment :: Console
Classifier: Programming Language :: Python :: 2.6
Classifier: Programming Language :: Python :: 2.7
Classifier: Programming Language :: Python :: 3.5
Classifier: Programming Language :: Python :: 3.6
